biopythonn/__init__.py
biopythonn/temp.py
biopythonn-0.1.2.dist-info/licenses/LICENSE
biopythonn-0.1.2.dist-info/METADATA
biopythonn-0.1.2.dist-info/WHEEL
biopythonn-0.1.2.dist-info/top_level.txt
biopythonn-0.1.2.dist-info/RECORD
